LICENSE
MANIFEST.in
README.md
requirements.txt
setup.py
mxene/__init__.py
mxene.egg-info/PKG-INFO
mxene.egg-info/SOURCES.txt
mxene.egg-info/dependency_links.txt
mxene.egg-info/requires.txt
mxene.egg-info/top_level.txt
mxene/apply/__init__.py
mxene/apply/infect.py
mxene/apply/structure_matcher.py
mxene/cli/__init__.py
mxene/core/__init__.py
mxene/core/functions.py
mxene/core/functions2.py
mxene/core/mxenes.py
mxene/extract/__init__.py
mxene/extract/structure_extractor.py
mxene/monitor/__init__.py
mxene/monitor/jobmanagement.py
mxene/organize/__init__.py
mxene/organize/change.py
mxene/organize/disk.py
mxene/organize/grid.py
mxene/organize/mx_org.py
mxene/organize/tree_plot.py
mxene/prepare/__init__.py
mxene/prepare/conf_files.py
mxene/prepare/incar_dict.py
mxene/prepare/pre_kpoints.py
mxene/prepare/pre_potcar.py
mxene/prepare/quick_input.py
mxene/prepare/vaspinput.py
mxene/utility/__init__.py
mxene/utility/typing.py
test/test_mxene.py
test/test_sp.py